src/mux/mux.v
/**************************************************************************************************
 * Copyright (c) 2025 Bayley King
 * Licensed under the MIT License
 **************************************************************************************************/
/*
 * Simple 4:1 MUX with enable and asynchronus reset
 * Associated test bench file: mut_tb.v
 * Developer: Bayley King
 */

module mux #(
    parameter DATA_WIDTH = 8
)(
    input [DATA_WIDTH:0] din_0,         // Input A
    input [DATA_WIDTH:0] din_1,         // Input B
    input [DATA_WIDTH:0] din_2,         // Input C
    input [DATA_WIDTH:0] din_3,         // Input D
    input [1:0] sel,                    // Select
    input reset_n,                      // Active low asynchronus reset
    input clk,                          // Clock input
    output reg [DATA_WIDTH:0] mux_out   // Output Bus
);

always @ (posedge clk, negedge reset_n, sel) begin
    if (reset_n == 0) begin
        mux_out = 0;
    end
    else begin
        case (sel)
            2'b00 : mux_out = din_0;
            2'b01 : mux_out = din_1;
            2'b10 : mux_out = din_2;
            2'b11 : mux_out = din_3;
        endcase
    end
end
endmodule

mux/tb/mux_tb.v
/**************************************************************************************************
 * Copyright (c) 2025 Bayley King
 * Licensed under the MIT License
 **************************************************************************************************/
/*
 * Simple 4:1 MUX with enable and asynchronus reset test bench
 * Associated design file: mut.v
 * Developer: Bayley King
 */
`timescale 10ns/1ns

module tb_mux;

// parameter initialization
parameter DATA_WIDTH = 8;
// reg and wire initialization
reg [DATA_WIDTH:0] din_0;         // Input A
reg [DATA_WIDTH:0] din_1;         // Input B
reg [DATA_WIDTH:0] din_2;         // Input C
reg [DATA_WIDTH:0] din_3;         // Input D
reg [1:0] sel;                    // Select
reg reset_n;                      // Active low asynchronus reset
reg clk;                          // Clock input
wire [DATA_WIDTH:0] mux_out;   // Output Bus

// design initialization
mux #(
    .DATA_WIDTH(DATA_WIDTH)
) mux0 (
    .din_0(din_0),
    .din_1(din_1),
    .din_2(din_2),
    .din_3(din_3),
    .sel(sel),
    .reset_n(reset_n),
    .clk(clk),
    .mux_out(mux_out)
);

initial begin
    // will output to debugger, with any change to a value
    $monitor ("[%0t] sel=0x%0h din_0=0x%0h din_1=0x%0h din_2=0x%0h din_3=0x%0h mux_out=0x%0h", 
              $time, sel, din_0, din_1, din_2, din_3, mux_out
    );

    // test cases initializations
    $display("Test 1");
    reset_n = 1;
    sel = 0;
    din_0 = $random;
    din_1 = $random;
    din_2 = $random;
    din_3 = $random;

    // run through selects
    loop_sel();
    #5;

    // toggle reset
    $display("Reset Toggle");
    reset_n = 0;
    #15 reset_n = 1;


    $display("Test 2");
    // randomize, and run again with reset high
    din_0 = $random;
    din_1 = $random;
    din_2 = $random;
    din_3 = $random;
    loop_sel();
    #5; $finish;

end

// Task to run through all 4 select options
// Just speeds up checking all values in the output
task loop_sel;
    integer i;
    for (i = 0; i < 4; i = i + 1) begin
        sel = i; #5;
    end

endtask

// Clock running forever
initial begin
    clk = 0;
    forever begin
        #5 clk = ~clk;
    end
end
endmodule

mux/sim/waves.vcd
$date
	Sun Nov 16 16:40:22 2025
$end
$version
	Icarus Verilog
$end
$timescale
	1ns
$end
$scope module tb_mux $end
$var wire 9 ! mux_out [8:0] $end
$var parameter 32 " DATA_WIDTH $end
$var reg 1 # clk $end
$var reg 9 $ din_0 [8:0] $end
$var reg 9 % din_1 [8:0] $end
$var reg 9 & din_2 [8:0] $end
$var reg 9 ' din_3 [8:0] $end
$var reg 1 ( reset_n $end
$var reg 2 ) sel [1:0] $end
$scope module mux0 $end
$var wire 1 # clk $end
$var wire 9 * din_0 [8:0] $end
$var wire 9 + din_1 [8:0] $end
$var wire 9 , din_2 [8:0] $end
$var wire 9 - din_3 [8:0] $end
$var wire 1 ( reset_n $end
$var wire 2 . sel [1:0] $end
$var parameter 32 / DATA_WIDTH $end
$var reg 9 0 mux_out [8:0] $end
$upscope $end
$scope task loop_sel $end
$var integer 32 1 i [31:0] $end
$upscope $end
$upscope $end
$enddefinitions $end
$comment Show the parameter values. $end
$dumpall
b1000 /
b1000 "
$end
#0
$dumpvars
b0 1
b100100100 0
b0 .
b1100011 -
b1001 ,
b10000001 +
b100100100 *
b0 )
1(
b1100011 '
b1001 &
b10000001 %
b100100100 $
0#
b100100100 !
$end
#50
b10000001 !
b10000001 0
1#
b1 )
b1 .
b1 1
#100
b1001 !
b1001 0
0#
b10 )
b10 .
b10 1
#150
b1100011 !
b1100011 0
1#
b11 )
b11 .
b11 1
#200
0#
b100 1
#250
b0 !
b0 0
1#
0(
#300
0#
#350
1#
#400
b100001101 !
b100001101 0
0#
b0 )
b0 .
b0 1
b10010 '
b10010 -
b1100101 &
b1100101 ,
b110001101 %
b110001101 +
b100001101 $
b100001101 *
1(
#450
b110001101 !
b110001101 0
1#
b1 )
b1 .
b1 1
#500
b1100101 !
b1100101 0
0#
b10 )
b10 .
b10 1
#550
b10010 !
b10010 0
1#
b11 )
b11 .
b11 1
#600
0#
b100 1
